soar_sml-9.6.4.dist-info/RECORD
soar_sml-9.6.4.dist-info/WHEEL
soar_sml-9.6.4.dist-info/entry_points.txt
soar_sml-9.6.4.dist-info/METADATA
soar_sml/libSoar.dylib
soar_sml/__init__.py
soar_sml/_Python_sml_ClientInterface.so
