Metadata-Version: 2.1
Name: soar-sml
Version: 9.6.4
Summary: Raw SML Bindings to the Soar Cognitive Architecture
Requires-Python: >=3.5
License: BSD
Author: John E. Laird, Allen Newell, Paul Rosenbloom, A. Deschamps, A. Mininger, A. Nickels, A. Nuxoll, A. Turner, B. Stearns, C. Dettmering, D. Pearson, D. Ray, I. Hines, J. Boggs, J. Crossman, J. Kirk, J. Li, J. Voigt, J. Xu, K. Coulter, L. Goeddel, M. Assanie, M. Bloch, M. Lanting, M. Schmidt, M. Tinkerhess, N. Derbinsky, N. Glenn, N. Gorski, N. Timpko, R. Marinier, R. Wray, S. Jones, S. Lathrop, S. Mohan, S. Nason, S. Wallace, S. Wintermute, Y. Wang
Maintainer-email: Nathan Glenn <garfieldnate@gmail.com>, Center for Integrated Cognition
Keywords: soar,sml,cog-arch,cognitive architecture,cognitive,soar-sml,ai
Classifier: Programming Language :: Python :: 3
Project-URL: Homepage, https://soar.eecs.umich.edu/
Project-URL: Repository, https://github.com/SoarGroup/Soar
Provides-Extra: compat
Requires-Dist: soar-compat; extra == 'compat'
